odoo/addons/l10n_es_aeat_soap/README.rst
odoo/addons/l10n_es_aeat_soap/__init__.py
odoo/addons/l10n_es_aeat_soap/__manifest__.py
odoo/addons/l10n_es_aeat_soap/i18n/ca.po
odoo/addons/l10n_es_aeat_soap/i18n/es.po
odoo/addons/l10n_es_aeat_soap/i18n/l10n_es_aeat_soap.pot
odoo/addons/l10n_es_aeat_soap/models/__init__.py
odoo/addons/l10n_es_aeat_soap/models/aeat_soap.py
odoo/addons/l10n_es_aeat_soap/static/description/icon.png
odoo11_addon_l10n_es_aeat_soap-11.0.0.1.1.dist-info/METADATA
odoo11_addon_l10n_es_aeat_soap-11.0.0.1.1.dist-info/WHEEL
odoo11_addon_l10n_es_aeat_soap-11.0.0.1.1.dist-info/top_level.txt
odoo11_addon_l10n_es_aeat_soap-11.0.0.1.1.dist-info/RECORD
